{"items": [{"id": "48675718", "premium": false, "name": "Специалист отдела продаж", "department": null, "has_test": false, "response_letter_required": false, "area": {"id": "84", "name": "Ставрополь", "url": "https://api.hh.ru/areas/84"}, "salary": {"from": 30000, "to": 45000, "currency": "RUR", "gross": true}, "type": {"id": "open", "name": "Открытая"}, "address": {"city": "Ставрополь", "street": "улица Мира", "building": "295/2", "description": null, "lat": 45.039018, "lng": 41.976459, "raw": "Ставрополь, улица Мира, 295/2", "metro": null, "metro_stations": [], "id": "1182560"}, "response_url": null, "sort_point_distance": null, "published_at": "2021-10-10T09:26:49+0300", "created_at": "2021-10-10T09:26:49+0300", "archived": false, "apply_alternate_url": "https://hh.ru/applicant/vacancy_response?vacancyId=48675718", "insider_interview": null, "url": "https://api.hh.ru/vacancies/48675718?host=hh.ru", "alternate_url": "https://hh.ru/vacancy/48675718", "relations": [], "employer": {"id": "3255710", "name": "Межрегиональный Контакт-Центр", "url": "https://api.hh.ru/employers/3255710", "alternate_url": "https://hh.ru/employer/3255710", "logo_urls": {"original": "https://hhcdn.ru/employer-logo-original/515723.png", "90": "https://hhcdn.ru/employer-logo/2504472.png", "240": "https://hhcdn.ru/employer-logo/2504473.png"}, "vacancies_url": "https://api.hh.ru/vacancies?employer_id=3255710", "trusted": true}, "snippet": {"requirement": "Быстрообучаемый, активный, и хотите реализовать свои амбиции. - Соблюдение стандартов телефонного общения (при этом живое общение и личное обаяние приветствуется)!", "responsibility": "Желаете развиваться в направлении продаж и работать с клиентами. - Презентация и продажа интересных продуктов действующим абонентам МТС. - Консультирование абонентов по..."}, "contacts": null, "schedule": {"id": "fullDay", "name": "Полный день"}, "working_days": [], "working_time_intervals": [{"id": "from_four_to_six_hours_in_a_day", "name": "Можно работать сменами по 4–6 часов в день"}], "working_time_modes": [], "accept_temporary": false}, {"id": "48676607", "premium": false, "name": "Менеджер отдела телемаркетинга", "department": null, "has_test": false, "response_letter_required": false, "area": {"id": "84", "name": "Ставрополь", "url": "https://api.hh.ru/areas/84"}, "salary": {"from": 30000, "to": null, "currency": "RUR", "gross": true}, "type": {"id": "open", "name": "Открытая"}, "address": {"city": "Ставрополь", "street": "улица Мира", "building": "295/2", "description": null, "lat": 45.039018, "lng": 41.976459, "raw": "Ставрополь, улица Мира, 295/2", "metro": null, "metro_stations": [], "id": "1182560"}, "response_url": null, "sort_point_distance": null, "published_at": "2021-10-10T11:26:51+0300", "created_at": "2021-10-10T11:26:51+0300", "archived": false, "apply_alternate_url": "https://hh.ru/applicant/vacancy_response?vacancyId=48676607", "insider_interview": null, "url": "https://api.hh.ru/vacancies/48676607?host=hh.ru", "alternate_url": "https://hh.ru/vacancy/48676607", "relations": [], "employer": {"id": "3255710", "name": "Межрегиональный Контакт-Центр", "url": "https://api.hh.ru/employers/3255710", "alternate_url": "https://hh.ru/employer/3255710", "logo_urls": {"original": "https://hhcdn.ru/employer-logo-original/515723.png", "90": "https://hhcdn.ru/employer-logo/2504472.png", "240": "https://hhcdn.ru/employer-logo/2504473.png"}, "vacancies_url": "https://api.hh.ru/vacancies?employer_id=3255710", "trusted": true}, "snippet": {"requirement": null, "responsibility": "Вести переговоры с клиентами компании, делать коммерческие предложения для продвижения нового продукта: мобильная связь+ домашний интернет и ТВ от МТС..."}, "contacts": null, "schedule": {"id": "fullDay", "name": "Полный день"}, "working_days": [], "working_time_intervals": [{"id": "from_four_to_six_hours_in_a_day", "name": "Можно работать сменами по 4–6 часов в день"}], "working_time_modes": [], "accept_temporary": false}, {"id": "48675079", "premium": false, "name": "Специалист по дистанционным продажам", "department": null, "has_test": false, "response_letter_required": false, "area": {"id": "84", "name": "Ставрополь", "url": "https://api.hh.ru/areas/84"}, "salary": {"from": 30000, "to": null, "currency": "RUR", "gross": true}, "type": {"id": "open", "name": "Открытая"}, "address": {"city": "Ставрополь", "street": "улица Мира", "building": "295/2", "description": null, "lat": 45.039018, "lng": 41.976459, "raw": "Ставрополь, улица Мира, 295/2", "metro": null, "metro_stations": [], "id": "1182560"}, "response_url": null, "sort_point_distance": null, "published_at": "2021-10-10T07:26:49+0300", "created_at": "2021-10-10T07:26:49+0300", "archived": false, "apply_alternate_url": "https://hh.ru/applicant/vacancy_response?vacancyId=48675079", "insider_interview": null, "url": "https://api.hh.ru/vacancies/48675079?host=hh.ru", "alternate_url": "https://hh.ru/vacancy/48675079", "relations": [], "employer": {"id": "3255710", "name": "Межрегиональный Контакт-Центр", "url": "https://api.hh.ru/employers/3255710", "alternate_url": "https://hh.ru/employer/3255710", "logo_urls": {"original": "https://hhcdn.ru/employer-logo-original/515723.png", "90": "https://hhcdn.ru/employer-logo/2504472.png", "240": "https://hhcdn.ru/employer-logo/2504473.png"}, "vacancies_url": "https://api.hh.ru/vacancies?employer_id=3255710", "trusted": true}, "snippet": {"requirement": "Доброжелательность. Знание офисных программ ПК. Ответственность.", "responsibility": "Продавать действующим абонентам мобильной связи МТС домашний интернет и ТВ."}, "contacts": null, "schedule": {"id": "fullDay", "name": "Полный день"}, "working_days": [], "working_time_intervals": [{"id": "from_four_to_six_hours_in_a_day", "name": "Можно работать сменами по 4–6 часов в день"}], "working_time_modes": [], "accept_temporary": false}, {"id": "48677081", "premium": false, "name": "Начинающий специалист по продажам", "department": null, "has_test": false, "response_letter_required": false, "area": {"id": "84", "name": "Ставрополь", "url": "https://api.hh.ru/areas/84"}, "salary": {"from": 30000, "to": null, "currency": "RUR", "gross": true}, "type": {"id": "open", "name": "Открытая"}, "address": {"city": "Ставрополь", "street": "улица Мира", "building": "295/2", "description": null, "lat": 45.039018, "lng": 41.976459, "raw": "Ставрополь, улица Мира, 295/2", "metro": null, "metro_stations": [], "id": "1182560"}, "response_url": null, "sort_point_distance": null, "published_at": "2021-10-10T12:26:50+0300", "created_at": "2021-10-10T12:26:50+0300", "archived": false, "apply_alternate_url": "https://hh.ru/applicant/vacancy_response?vacancyId=48677081", "insider_interview": null, "url": "https://api.hh.ru/vacancies/48677081?host=hh.ru", "alternate_url": "https://hh.ru/vacancy/48677081", "relations": [], "employer": {"id": "3255710", "name": "Межрегиональный Контакт-Центр", "url": "https://api.hh.ru/employers/3255710", "alternate_url": "https://hh.ru/employer/3255710", "logo_urls": {"original": "https://hhcdn.ru/employer-logo-original/515723.png", "90": "https://hhcdn.ru/employer-logo/2504472.png", "240": "https://hhcdn.ru/employer-logo/2504473.png"}, "vacancies_url": "https://api.hh.ru/vacancies?employer_id=3255710", "trusted": true}, "snippet": {"requirement": "Элементарные знание офисных программ ПК. - Ответственный подход.", "responsibility": null}, "contacts": null, "schedule": {"id": "fullDay", "name": "Полный день"}, "working_days": [], "working_time_intervals": [{"id": "from_four_to_six_hours_in_a_day", "name": "Можно работать сменами по 4–6 часов в день"}], "working_time_modes": [], "accept_temporary": false}, {"id": "48676087", "premium": false, "name": "Специалист отдела телемаркетинга (МТС)", "department": null, "has_test": false, "response_letter_required": false, "area": {"id": "84", "name": "Ставрополь", "url": "https://api.hh.ru/areas/84"}, "salary": {"from": 30000, "to": null, "currency": "RUR", "gross": false}, "type": {"id": "open", "name": "Открытая"}, "address": {"city": "Ставрополь", "street": "улица Мира", "building": "295/2", "description": null, "lat": 45.039018, "lng": 41.976459, "raw": "Ставрополь, улица Мира, 295/2", "metro": null, "metro_stations": [], "id": "1182560"}, "response_url": null, "sort_point_distance": null, "published_at": "2021-10-10T10:26:50+0300", "created_at": "2021-10-10T10:26:50+0300", "archived": false, "apply_alternate_url": "https://hh.ru/applicant/vacancy_response?vacancyId=48676087", "insider_interview": null, "url": "https://api.hh.ru/vacancies/48676087?host=hh.ru", "alternate_url": "https://hh.ru/vacancy/48676087", "relations": [], "employer": {"id": "3255710", "name": "Межрегиональный Контакт-Центр", "url": "https://api.hh.ru/employers/3255710", "alternate_url": "https://hh.ru/employer/3255710", "logo_urls": {"original": "https://hhcdn.ru/employer-logo-original/515723.png", "90": "https://hhcdn.ru/employer-logo/2504472.png", "240": "https://hhcdn.ru/employer-logo/2504473.png"}, "vacancies_url": "https://api.hh.ru/vacancies?employer_id=3255710", "trusted": true}, "snippet": {"requirement": "Опыт не требуется! Всему научим!", "responsibility": "Совершать исходящие звонки нашим клиентам, которые уже пользуются мобильными услугами МТС и предлагать подключить еще и домашний интернет и ТВ..."}, "contacts": null, "schedule": {"id": "fullDay", "name": "Полный день"}, "working_days": [], "working_time_intervals": [{"id": "from_four_to_six_hours_in_a_day", "name": "Можно работать сменами по 4–6 часов в день"}], "working_time_modes": [], "accept_temporary": false}, {"id": "48670816", "premium": false, "name": "Выездной Компьютерный мастер в Саранске", "department": null, "has_test": false, "response_letter_required": false, "area": {"id": "63", "name": "Саранск", "url": "https://api.hh.ru/areas/63"}, "salary": {"from": 50000, "to": null, "currency": "RUR", "gross": false}, "type": {"id": "open", "name": "Открытая"}, "address": null, "response_url": null, "sort_point_distance": null, "published_at": "2021-10-09T16:47:05+0300", "created_at": "2021-10-09T16:47:05+0300", "archived": false, "apply_alternate_url": "https://hh.ru/applicant/vacancy_response?vacancyId=48670816", "insider_interview": null, "url": "https://api.hh.ru/vacancies/48670816?host=hh.ru", "alternate_url": "https://hh.ru/vacancy/48670816", "relations": [], "employer": {"id": "4443801", "name": "Глебов Глеб Александрович", "url": "https://api.hh.ru/employers/4443801", "alternate_url": "https://hh.ru/employer/4443801", "logo_urls": {"90": "https://hhcdn.ru/employer-logo/4055507.png", "240": "https://hhcdn.ru/employer-logo/4055508.png", "original": "https://hhcdn.ru/employer-logo-original/903705.png"}, "vacancies_url": "https://api.hh.ru/vacancies?employer_id=4443801", "trusted": true}, "snippet": {"requirement": "Уверенные знания устройства и настройки компьютеров и ноутбуков. Умение устанавливать, переустанавливать Windows, а также сопутствующее ПО. Способность разобрать, почистить внутри...", "responsibility": "Ремонт и настройка компьютерной техники на выезде у клиента. Установка и настройка программного обеспечения. Удаление вирусов и смс-баннеров. "}, "contacts": null, "schedule": {"id": "fullDay", "name": "Полный день"}, "working_days": [], "working_time_intervals": [], "working_time_modes": [], "accept_temporary": false}, {"id": "48675291", "premium": false, "name": "Специалист обработки электронных заявок", "department": {"id": "2492-2492-14882", "name": "Московский Кредитный Банк. Молодые специалисты "}, "has_test": false, "response_letter_required": false, "area": {"id": "72", "name": "Пермь", "url": "https://api.hh.ru/areas/72"}, "salary": {"from": 34000, "to": null, "currency": "RUR", "gross": true}, "type": {"id": "open", "name": "Открытая"}, "address": {"city": "Пермь", "street": "улица Крисанова", "building": "59", "description": null, "lat": 58.002143, "lng": 56.215169, "raw": "Пермь, улица Крисанова, 59", "metro": null, "metro_stations": [], "id": "3827638"}, "response_url": null, "sort_point_distance": null, "published_at": "2021-10-10T08:09:07+0300", "created_at": "2021-10-10T08:09:07+0300", "archived": false, "apply_alternate_url": "https://hh.ru/applicant/vacancy_response?vacancyId=48675291", "insider_interview": null, "url": "https://api.hh.ru/vacancies/48675291?host=hh.ru", "alternate_url": "https://hh.ru/vacancy/48675291", "relations": [], "employer": {"id": "2492", "name": "Московский Кредитный Банк", "url": "https://api.hh.ru/employers/2492", "alternate_url": "https://hh.ru/employer/2492", "logo_urls": {"90": "https://hhcdn.ru/employer-logo/3216280.png", "240": "https://hhcdn.ru/employer-logo/3216281.png", "original": "https://hhcdn.ru/employer-logo-original/693791.png"}, "vacancies_url": "https://api.hh.ru/vacancies?employer_id=2492", "trusted": true}, "snippet": {"requirement": "Начинающий специалист без опыта работы, желающий строить карьеру в банковской сфере. Имеешь возможность работать полный день. Имеешь хорошую дикцию и...", "responsibility": "Обрабатывать входящие заявки от потенциальных клиентов Банка (заявки поступают через сайт Банка или банковские сервисы). Назначать встречи клиентам по продуктам..."}, "contacts": null, "schedule": {"id": "fullDay", "name": "Полный день"}, "working_days": [], "working_time_intervals": [], "working_time_modes": [], "accept_temporary": false}, {"id": "48676082", "premium": false, "name": "Менеджер по продаже недвижимости / Риэлтор", "department": null, "has_test": false, "response_letter_required": false, "area": {"id": "237", "name": "Сочи", "url": "https://api.hh.ru/areas/237"}, "salary": {"from": 89999, "to": 399999, "currency": "RUR", "gross": false}, "type": {"id": "open", "name": "Открытая"}, "address": {"city": "Сочи", "street": "микрорайон Центральный, улица Горького", "building": "53", "description": null, "lat": 43.589965, "lng": 39.726215, "raw": "Сочи, микрорайон Центральный, улица Горького, 53", "metro": null, "metro_stations": [], "id": "5615345"}, "response_url": null, "sort_point_distance": null, "published_at": "2021-10-10T10:26:49+0300", "created_at": "2021-10-10T10:26:49+0300", "archived": false, "apply_alternate_url": "https://hh.ru/applicant/vacancy_response?vacancyId=48676082", "insider_interview": null, "url": "https://api.hh.ru/vacancies/48676082?host=hh.ru", "alternate_url": "https://hh.ru/vacancy/48676082", "relations": [], "employer": {"id": "2980663", "name": "FLЭTHOUSE", "url": "https://api.hh.ru/employers/2980663", "alternate_url": "https://hh.ru/employer/2980663", "logo_urls": {"240": "https://hhcdn.ru/employer-logo/3981372.jpeg", "90": "https://hhcdn.ru/employer-logo/3981371.jpeg", "original": "https://hhcdn.ru/employer-logo-original/885168.jpg"}, "vacancies_url": "https://api.hh.ru/vacancies?employer_id=2980663", "trusted": true}, "snippet": {"requirement": null, "responsibility": "Входящий поток клиентов. ✓ Автоматизированная система работы с клиентами."}, "contacts": null, "schedule": {"id": "fullDay", "name": "Полный день"}, "working_days": [], "working_time_intervals": [], "working_time_modes": [], "accept_temporary": true}], "found": 8, "pages": 1, "per_page": 100, "page": 0, "clusters": null, "arguments": null, "alternate_url": "https://hh.ru/search/vacancy?area=113&date_from=09.10.2021+15%3A32%3A42&date_to=10.10.2021+15%3A32%3A42&enable_snippets=true&experience=noExperience&items_on_page=100&label=not_from_agency&specialization=1.225"}